wagtail_tinytableblock/__init__.py
wagtail_tinytableblock/__version__.py
wagtail_tinytableblock/blocks.py
wagtail_tinytableblock/utils.py
wagtail_tinytableblock/static/wagtail_tinytableblock/js/tiny-table-block.js
wagtail_tinytableblock/static/wagtail_tinytableblock/js/vendor/tinymce/license.md
wagtail_tinytableblock/static/wagtail_tinytableblock/js/vendor/tinymce/tinymce.min.js
wagtail_tinytableblock/static/wagtail_tinytableblock/js/vendor/tinymce/icons/default/icons.min.js
wagtail_tinytableblock/static/wagtail_tinytableblock/js/vendor/tinymce/models/dom/model.min.js
wagtail_tinytableblock/static/wagtail_tinytableblock/js/vendor/tinymce/plugins/autolink/plugin.min.js
wagtail_tinytableblock/static/wagtail_tinytableblock/js/vendor/tinymce/plugins/autoresize/plugin.min.js
wagtail_tinytableblock/static/wagtail_tinytableblock/js/vendor/tinymce/plugins/link/plugin.min.js
wagtail_tinytableblock/static/wagtail_tinytableblock/js/vendor/tinymce/plugins/table/plugin.min.js
wagtail_tinytableblock/static/wagtail_tinytableblock/js/vendor/tinymce/skins/content/dark/content.js
wagtail_tinytableblock/static/wagtail_tinytableblock/js/vendor/tinymce/skins/content/dark/content.min.css
wagtail_tinytableblock/static/wagtail_tinytableblock/js/vendor/tinymce/skins/content/default/content.js
wagtail_tinytableblock/static/wagtail_tinytableblock/js/vendor/tinymce/skins/content/default/content.min.css
wagtail_tinytableblock/static/wagtail_tinytableblock/js/vendor/tinymce/skins/ui/oxide/content.inline.js
wagtail_tinytableblock/static/wagtail_tinytableblock/js/vendor/tinymce/skins/ui/oxide/content.inline.min.css
wagtail_tinytableblock/static/wagtail_tinytableblock/js/vendor/tinymce/skins/ui/oxide/content.js
wagtail_tinytableblock/static/wagtail_tinytableblock/js/vendor/tinymce/skins/ui/oxide/content.min.css
wagtail_tinytableblock/static/wagtail_tinytableblock/js/vendor/tinymce/skins/ui/oxide/skin.js
wagtail_tinytableblock-0.3.4.dist-info/licenses/LICENSE
wagtail_tinytableblock-0.3.4.dist-info/WHEEL
wagtail_tinytableblock-0.3.4.dist-info/METADATA
wagtail_tinytableblock-0.3.4.dist-info/RECORD
