Metadata-Version: 2.4
Name: wagtail-tinytableblock
Version: 0.3.4
Summary: A Wagtail StreamField block powered by TinyMCE and its table plugin
Keywords: Wagtail,Django,StreamField,TinyMCE,Tables
Author-email: Dan Braghis <dan.braghis@torchbox.com>
Maintainer-email: Dan Braghis <dan.braghis@torchbox.com>
Requires-Python: >=3.12
License-Expression: GPL-3.0-or-later
Classifier: Development Status :: 3 - Alpha
Classifier: Intended Audience :: Developers
Classifier: Operating System :: OS Independent
Classifier: Programming Language :: Python
Classifier: Programming Language :: Python :: 3
Classifier: Programming Language :: Python :: 3.12
Classifier: Programming Language :: Python :: 3.13
Classifier: Framework :: Django
Classifier: Framework :: Django :: 4.2
Classifier: Framework :: Django :: 5.1
Classifier: Framework :: Django :: 5.2
Classifier: Framework :: Wagtail
Classifier: Framework :: Wagtail :: 6
License-File: LICENSE
Requires-Dist: Django>=4.2
Requires-Dist: Wagtail>=6.3
Requires-Dist: nh3>=0.2.21,<0.3
Requires-Dist: dj-database-url>=2.1.0,<3.0 ; extra == "testing"
Requires-Dist: coverage>=7.0,<8.0 ; extra == "testing"
Project-URL: Changelog, https://github.com/torchbox/wagtail-tinytableblock/blob/main/CHANGELOG.md
Project-URL: Source, https://github.com/torchbox/wagtail-tinytableblock
Provides-Extra: testing
